optic_object_wavefronts/__init__.py
optic_object_wavefronts/delaunay.py
optic_object_wavefronts/export.py
optic_object_wavefronts/mesh.py
optic_object_wavefronts/minkowski.py
optic_object_wavefronts/plot.py
optic_object_wavefronts/polygon.py
optic_object_wavefronts/version.py
optic_object_wavefronts/geometry/__init__.py
optic_object_wavefronts/geometry/ellipse.py
optic_object_wavefronts/geometry/line.py
optic_object_wavefronts/geometry/parabola.py
optic_object_wavefronts/geometry/plane.py
optic_object_wavefronts/geometry/regular_polygon.py
optic_object_wavefronts/geometry/schmidt_corrector.py
optic_object_wavefronts/geometry/schwarzschild_couder.py
optic_object_wavefronts/geometry/sphere.py
optic_object_wavefronts/geometry/grid/__init__.py
optic_object_wavefronts/geometry/grid/hexagonal.py
optic_object_wavefronts/geometry/grid/rectangular.py
optic_object_wavefronts/geometry/grid/template.py
optic_object_wavefronts/optics/__init__.py
optic_object_wavefronts/optics/lens_maker.py
optic_object_wavefronts/optics/schmidt_corrector.py
optic_object_wavefronts/primitives/__init__.py
optic_object_wavefronts/primitives/cylinder.py
optic_object_wavefronts/primitives/disc.py
optic_object_wavefronts/primitives/light_field_eye.py
optic_object_wavefronts/primitives/parabolic_cap.py
optic_object_wavefronts/primitives/parabolic_cap_regular.py
optic_object_wavefronts/primitives/pipe_hexagonal.py
optic_object_wavefronts/primitives/plane.py
optic_object_wavefronts/primitives/rectangle.py
optic_object_wavefronts/primitives/schmidt_corrector_plate.py
optic_object_wavefronts/primitives/schmidt_corrector_surface.py
optic_object_wavefronts/primitives/schwarzschild_couder_cap.py
optic_object_wavefronts/primitives/spherical_cap.py
optic_object_wavefronts/primitives/spherical_cap_hexagonal.py
optic_object_wavefronts/primitives/spherical_cap_pixels.py
optic_object_wavefronts/primitives/spherical_cap_regular.py
optic_object_wavefronts/primitives/spherical_lens.py
optic_object_wavefronts-1.3.17.dist-info/licenses/LICENSE
optic_object_wavefronts-1.3.17.dist-info/METADATA
optic_object_wavefronts-1.3.17.dist-info/WHEEL
optic_object_wavefronts-1.3.17.dist-info/top_level.txt
optic_object_wavefronts-1.3.17.dist-info/RECORD
