Metadata-Version: 2.4
Name: optic_object_wavefronts
Version: 1.3.17
Summary: Representing optical components using object wavefronts
Home-page: https://github.com/cherenkov-plenoscope/optic_object_wavefronts
Author: Sebastian Achim Mueller
Author-email: sebastian-achim.mueller@mpi-hd.mpg.de
Classifier: Programming Language :: Python :: 3
Classifier: License :: OSI Approved :: MIT License
Classifier: Operating System :: OS Independent
Classifier: Natural Language :: English
Classifier: Intended Audience :: Science/Research
Classifier: Topic :: Scientific/Engineering :: Physics
Classifier: Topic :: Scientific/Engineering :: Astronomy
License-File: LICENSE
Requires-Dist: shapely
Requires-Dist: scipy
Requires-Dist: triangle_mesh_io>=0.1.3
Requires-Dist: json-numpy-sebastian-achim-mueller>=0.1.1
Dynamic: author
Dynamic: author-email
Dynamic: classifier
Dynamic: description
Dynamic: description-content-type
Dynamic: home-page
Dynamic: license-file
Dynamic: requires-dist
Dynamic: summary
